{
    "time_posted": "2021-10-30 16:00:05",
    "url": "https://www.youtube.com/watch?v=6dOqeFBvvZs",
    "time_now": "2021-10-31 05:04:32",
    "ups": "23476",
    "downs": "153",
    "views": "272182",
    "top_comments": [
        {
            "comment": "Why didn't you convert the stone into moss with bone meal?! \ud83e\udd14\nAnyways, the area is looking really cool \ud83d\udc4d",
            "likes": 1,
            "number_of_replies": 0,
            "polarity": 0.35,
            "subjectivity": 0.65
        },
        {
            "comment": "At 20:51 Iskall sounds just like the old Minecraft damage sound lol (I watch videos on 2x speed)",
            "likes": 1,
            "number_of_replies": 0,
            "polarity": 0.43333333333333335,
            "subjectivity": 0.43333333333333335
        }
    ],
    "comments_since_last_sample": [
        {
            "body": "Use moss carpets with lights underneath to light up the area :)",
            "polarity": 0.45,
            "subjectivity": 0.85
        },
        {
            "body": "I really think soul fire is needed to be in there anywhere.... I mean, blue fire would make it look omega enchanted...",
            "polarity": -0.0375,
            "subjectivity": 0.32916666666666666
        },
        {
            "body": "ISKALL SIRRRRR PLEASE ADD SPORE BLOSSOM ON TREES \ud83d\ude05",
            "polarity": 0.0,
            "subjectivity": 0.0
        },
        {
            "body": "Looks like a cat.",
            "polarity": 0.0,
            "subjectivity": 0.0
        },
        {
            "body": "the tunnel and elevator are not it they need a little bit of rounding and less of blockyness",
            "polarity": -0.17708333333333331,
            "subjectivity": 0.2833333333333333
        },
        {
            "body": "That was genuinly a very convincing ad spot well done",
            "polarity": 0.65,
            "subjectivity": 1.0
        },
        {
            "body": "I love the height of the walls in the cavern you made. I think it would be cool if the plant life had height too! Maybe some taller (and optionally skinnier?) trees, or vines/glow berries hanging down parts of the cliff (using string to limit their growth) or even some nether plant vines if you want a splash of blue or red somewhere",
            "polarity": 0.15638888888888888,
            "subjectivity": 0.32777777777777783
        },
        {
            "body": "Ahh thank god another lovely (omega) hermit craft video :)\u2665\ufe0f",
            "polarity": 0.5,
            "subjectivity": 0.875
        },
        {
            "body": "The amethyst glowstone tinted glass effect is INCREDIBLE",
            "polarity": 0.9,
            "subjectivity": 0.9
        },
        {
            "body": "Glazed Terracotta blocks might look cool in the water elevator! Either pink arrow ones to show you go up, or another color gradient!",
            "polarity": 0.15625,
            "subjectivity": 0.475
        },
        {
            "body": "The path looks so good and the blocks is something you wouldn\u2019t think of using",
            "polarity": 0.7,
            "subjectivity": 0.6000000000000001
        },
        {
            "body": "Melon blocks also work great in green gradients!",
            "polarity": 0.275,
            "subjectivity": 0.525
        },
        {
            "body": "Great Video Iskall, keep up the good work. I myself have started uploading videos to YouTube. Hopefully I get to where you are one day!!",
            "polarity": 0.9,
            "subjectivity": 0.675
        },
        {
            "body": "At 20:51 Iskall sounds just like the old Minecraft damage sound lol (I watch videos on 2x speed)",
            "polarity": 0.43333333333333335,
            "subjectivity": 0.43333333333333335
        },
        {
            "body": "These last two building videos are like watching 3D Bob Ross",
            "polarity": 0.0,
            "subjectivity": 0.06666666666666667
        },
        {
            "body": "Why didn't you convert the stone into moss with bone meal?! \ud83e\udd14\nAnyways, the area is looking really cool \ud83d\udc4d",
            "polarity": 0.35,
            "subjectivity": 0.65
        },
        {
            "body": "sea lanterns might look better than glowstone in the elevator.",
            "polarity": 0.5,
            "subjectivity": 0.5
        },
        {
            "body": "The crystal in the entrance pillars makes it look like a cat lol 20:10",
            "polarity": 0.8,
            "subjectivity": 0.7
        },
        {
            "body": "Make a waterfall or turn the elevator into waterfall",
            "polarity": 0.0,
            "subjectivity": 0.0
        }
    ]
}